discreteTimeAnalysis.py
discreteTimeAnalysis-1.0.1.dist-info/LICENSE
discreteTimeAnalysis-1.0.1.dist-info/METADATA
discreteTimeAnalysis-1.0.1.dist-info/WHEEL
discreteTimeAnalysis-1.0.1.dist-info/top_level.txt
discreteTimeAnalysis-1.0.1.dist-info/RECORD
