Metadata-Version: 2.1
Name: discreteTimeAnalysis
Version: 1.0.1
Summary: The module provides a class for finite discrete distributions which are utilized for discrete-time analysis. For example, discrete-time GI/GI/1 systems can be analyzed with functions of the module.
Author-email: Tobias Hossfeld <tobias.hossfeld@uni-wuerzburg.de>
License: Creativ Commons Attribution-ShareAlike 4.0 International [CC BY-SA 4.0]
Project-URL: Homepage, https://modeling.systems/
Project-URL: Github, https://hossfeld.github.io/performance-modeling/
Project-URL: Documentation, https://hossfeld.github.io/performance-modeling/chapter6_discreteTimeAnalysis/discreteTimeAnalysis.html
Keywords: discrete-time analysis,queueing system,GI/GI/1
Classifier: License :: Other/Proprietary License
Classifier: Programming Language :: Python
Classifier: Programming Language :: Python :: 3
Requires-Python: >=3.7
License-File: LICENSE
Requires-Dist: numpy
Requires-Dist: matplotlib
